[
  {
    "type": "ChildParent",
    "explanation": "Diem is the child of Thien."
  },
  {
    "type": "ChildParent",
    "explanation": "Diem is the child of Thien"
  },
  {
    "type": "ChildParent",
    "explanation": "Diem is the child of Thien"
  },
  {
    "type": "ChildParent",
    "explanation": "Diem is the child of Thien"
  },
  {
    "type": "ChildParent",
    "explanation": "Diem is the child of Thien."
  },
  {
    "type": "ChildParent",
    "explanation": "Diem is the parent of Thien."
  },
  {
    "type": "ChildParent",
    "explanation": "Diem is the child of Thien"
  },
  {
    "type": "ChildParent",
    "explanation": "Diem is the child of Thien"
  },
  {
    "type": "ChildParent",
    "explanation": "Diem is the child of Thien."
  },
  {
    "type": "Child-Other Family Elder",
    "explanation": "Diem is a child of Thien"
  }
]