[
  {
    "type": "ChildParent",
    "explanation": "Ling is Nghia's parent."
  },
  {
    "type": "ChildParent",
    "explanation": "Nghia and Ling are siblings."
  },
  {
    "type": "ChildParent",
    "explanation": "Nghia is the child of Ling."
  },
  {
    "type": "ChildParent",
    "explanation": "Nghia is the child of Ling"
  },
  {
    "type": "ChildParent",
    "explanation": "Based on the conversation, Nghia is a child of Ling."
  },
  {
    "type": "ChildParent",
    "explanation": "Nghia is the child of Ling"
  },
  {
    "type": "ChildParent",
    "explanation": "Nghia is the child of Ling"
  },
  {
    "type": "ChildParent",
    "explanation": "Nghia is the child of Ling"
  },
  {
    "type": "ChildParent",
    "explanation": "Based on the conversation, it is inferred that Nghia is the child of Ling."
  },
  {
    "type": "ChildParent",
    "explanation": "Both are children of the same parent."
  },
  {
    "type": "Lovers",
    "explanation": "The conversation between Nghia and Ling is a conversation between lovers."
  },
  {
    "type": "ChildParent",
    "explanation": "Ling is the child of Nghia"
  },
  {
    "type": "Lovers",
    "explanation": "Based on the conversation, it is inferred that Nghia and Ling are lovers."
  },
  {
    "type": "ChildParent",
    "explanation": "Nghia is a child of Ling"
  },
  {
    "type": "ChildParent",
    "explanation": "Ling is the parent of Nghia"
  },
  {
    "type": "ChildParent",
    "explanation": "Nghia is the child of Ling"
  },
  {
    "type": "ChildParent",
    "explanation": "Nghia is the child of Ling"
  },
  {
    "type": "Lovers",
    "explanation": "Both are lovers."
  },
  {
    "type": "ChildParent",
    "explanation": "Nghia is a child of Ling"
  },
  {
    "type": "Lovers",
    "explanation": "The conversation between Nghia and Ling is a conversation between lovers."
  },
  {
    "type": "ChildParent",
    "explanation": "Nghia is a child of Ling"
  },
  {
    "type": "ChildParent",
    "explanation": "Nghia is a child of Ling"
  },
  {
    "type": "ChildParent",
    "explanation": "Nghia is a child of Ling"
  },
  {
    "type": "ChildParent",
    "explanation": "Nghia is a child of Ling"
  },
  {
    "type": "ChildParent",
    "explanation": "Nghia is a child of Ling"
  },
  {
    "type": "ChildParent",
    "explanation": "Nghia is a child of Ling"
  },
  {
    "type": "Lovers",
    "explanation": "The conversation between Nghia and Ling is a conversation between lovers."
  },
  {
    "type": "ChildParent",
    "explanation": "Because I asked you. And..."
  },
  {
    "type": "Friends",
    "explanation": "Both are friends."
  },
  {
    "type": "ChildParent",
    "explanation": "Nghia is the child of Ling"
  },
  {
    "type": "ChildParent",
    "explanation": "Ling is the child of Nghia"
  },
  {
    "type": "ChildParent",
    "explanation": "The conversation between Nghia and Ling is between a child and a parent."
  },
  {
    "type": "ChildParent",
    "explanation": "Nghia is the child of Ling"
  },
  {
    "type": "Friends",
    "explanation": "Both are friends."
  },
  {
    "type": "ChildParent",
    "explanation": "Nghia is the child of Ling"
  },
  {
    "type": "ChildParent",
    "explanation": "Nghia is a child of Ling"
  },
  {
    "type": "ChildParent",
    "explanation": "Nghia is the child of Ling"
  },
  {
    "type": "Lovers",
    "explanation": "The conversation between Nghia and Ling is a conversation between lovers."
  },
  {
    "type": "ChildParent",
    "explanation": "Nghia is the child of Ling"
  }
]