[
  {
    "type": "ChildParent",
    "explanation": "Quoc is the child of Thuan."
  },
  {
    "type": "ChildParent",
    "explanation": "Quoc is the child of Thuan"
  },
  {
    "type": "ChildParent",
    "explanation": "Quoc is the child of Thuan"
  },
  {
    "type": "ChildParent",
    "explanation": "Quoc is the child of Thuan"
  },
  {
    "type": "ChildParent",
    "explanation": "Quoc is the child of Thuan."
  },
  {
    "type": "ChildParent",
    "explanation": "Quoc is the child of Thuan"
  },
  {
    "type": "ChildParent",
    "explanation": "Quoc is the child of Thuan"
  },
  {
    "type": "Friends",
    "explanation": "Quoc and Thuan are friends."
  },
  {
    "type": "ChildParent",
    "explanation": "Quoc is the child of Thuan"
  },
  {
    "type": "ChildParent",
    "explanation": "Quoc is the child of Thuan"
  }
]