[
  {
    "type": "ChildParent",
    "explanation": "Sung is the child of Jie."
  },
  {
    "type": "ChildParent",
    "explanation": "Sung is the child of Jie."
  },
  {
    "type": "ChildParent",
    "explanation": "Sung is the child of Jie."
  },
  {
    "type": "ChildParent",
    "explanation": "Jie is the child of Sung."
  },
  {
    "type": "ChildParent",
    "explanation": "Sung and Jie are siblings."
  },
  {
    "type": "ChildParent",
    "explanation": "Sung is the child of Jie."
  },
  {
    "type": "ChildParent",
    "explanation": "Sung is a child of Jie."
  },
  {
    "type": "ChildParent",
    "explanation": "Jie is Sung's child."
  },
  {
    "type": "ChildParent",
    "explanation": "Sung is a child of Jie."
  },
  {
    "type": "ChildParent",
    "explanation": "Sung is a child of Jie"
  }
]