[
  {
    "type": "ChildParent",
    "explanation": "Huong is Thuan's child."
  },
  {
    "type": "ChildParent",
    "explanation": "Thuan and Huong are siblings."
  },
  {
    "type": "ChildParent",
    "explanation": "Thuan is Huong's child."
  },
  {
    "type": "ChildParent",
    "explanation": "Thuan is Huong's child."
  },
  {
    "type": "ChildParent",
    "explanation": "Thuan is Huong's child."
  },
  {
    "type": "ChildParent",
    "explanation": "Thuan is Huong's child."
  },
  {
    "type": "ChildParent",
    "explanation": "Thuan is the child of Huong."
  },
  {
    "type": "ChildParent",
    "explanation": "Thuan is Huong's child."
  },
  {
    "type": "ChildParent",
    "explanation": "Thuan is Huong's child."
  },
  {
    "type": "ChildParent",
    "explanation": "Thuan is Huong's child."
  },
  {
    "type": "Lovers",
    "explanation": "The conversation between Thuan and Huong is a conversation between lovers."
  },
  {
    "type": "Lovers",
    "explanation": "The conversation between Thuan and Huong is about a romantic relationship."
  },
  {
    "type": "Lovers",
    "explanation": "Thuan and Huong are lovers."
  },
  {
    "type": "ChildParent",
    "explanation": "Thuan is Huong's child."
  },
  {
    "type": "ChildParent",
    "explanation": "Huong is the child of Thuan."
  },
  {
    "type": "ChildParent",
    "explanation": "Thuan is Huong's child."
  },
  {
    "type": "ChildParent",
    "explanation": "Thuan and Huong are siblings."
  },
  {
    "type": "Lovers",
    "explanation": "Thuan and Huong are lovers."
  },
  {
    "type": "ChildParent",
    "explanation": "Thuan is Huong's child."
  },
  {
    "type": "Lovers",
    "explanation": "The conversation between Thuan and Huong is a conversation between lovers."
  },
  {
    "type": "ChildParent",
    "explanation": "Thuan is a child of Huong"
  },
  {
    "type": "ChildParent",
    "explanation": "Thuan is a child of Huong"
  },
  {
    "type": "ChildParent",
    "explanation": "Thuan is a child of Huong."
  },
  {
    "type": "Lovers",
    "explanation": "Thuan and Huong are in a relationship."
  },
  {
    "type": "ChildParent",
    "explanation": "Thuan is the child of Huong"
  },
  {
    "type": "Lovers",
    "explanation": "Thuan and Huong are lovers."
  },
  {
    "type": "ChildParent",
    "explanation": "Thuan is a child of Huong"
  },
  {
    "type": "ChildParent",
    "explanation": "Because I asked you. And..."
  },
  {
    "type": "ChildParent",
    "explanation": "Thuan is a child of Huong"
  },
  {
    "type": "ChildParent",
    "explanation": "Thuan is the child of Huong"
  },
  {
    "type": "ChildParent",
    "explanation": "Thuan is Huong's child."
  },
  {
    "type": "ChildParent",
    "explanation": "Huong is the child of Thuan"
  },
  {
    "type": "Lovers",
    "explanation": "The conversation between Thuan and Huong is a conversation between lovers."
  },
  {
    "type": "Lovers",
    "explanation": "The two people are lovers."
  },
  {
    "type": "Friends",
    "explanation": "Thuan and Huong are friends."
  },
  {
    "type": "ChildParent",
    "explanation": "Thuan is the child of Huong"
  },
  {
    "type": "ChildParent",
    "explanation": "Thuan is Huong's child."
  },
  {
    "type": "ChildParent",
    "explanation": "Thuan is Huong's parent."
  },
  {
    "type": "Lovers",
    "explanation": "The conversation between Thuan and Huong is a conversation between lovers."
  },
  {
    "type": "Lovers",
    "explanation": "Thuan and Huong are lovers."
  }
]