[
  {
    "type": "ChildParent",
    "explanation": "Thuan is the child of Nghia"
  },
  {
    "type": "ChildParent",
    "explanation": "Thuan is the child of Nghia"
  },
  {
    "type": "ChildParent",
    "explanation": "Thuan is the child of Nghia"
  },
  {
    "type": "ChildParent",
    "explanation": "Thuan is the child of Nghia"
  },
  {
    "type": "ChildParent",
    "explanation": "Thuan is the child of Nghia"
  },
  {
    "type": "ChildParent",
    "explanation": "Thuan is the child of Nghia"
  },
  {
    "type": "ChildParent",
    "explanation": "Thuan is the child of Nghia"
  },
  {
    "type": "ChildParent",
    "explanation": "Thuan is Nghia's child."
  },
  {
    "type": "ChildParent",
    "explanation": "Thuan is the child of Nghia"
  },
  {
    "type": "Child-Other Family Elder",
    "explanation": "Thuan is a child of Nghia's other family elder."
  }
]