[
  {
    "type": "ChildParent",
    "explanation": "Wen is a child of Vy."
  },
  {
    "type": "ChildParent",
    "explanation": "Wen is the child of Vy"
  },
  {
    "type": "ChildParent",
    "explanation": "Wen is the child of Vy"
  },
  {
    "type": "ChildParent",
    "explanation": "Wen is the child of Vy"
  },
  {
    "type": "ChildParent",
    "explanation": "Wen and Vy are siblings."
  },
  {
    "type": "ChildParent",
    "explanation": "Wen is the parent of Vy"
  },
  {
    "type": "ChildParent",
    "explanation": "Wen is a child of Vy"
  },
  {
    "type": "ChildParent",
    "explanation": "Wen is the child of Vy"
  },
  {
    "type": "ChildParent",
    "explanation": "Wen is the child of Vy."
  },
  {
    "type": "Child-Other Family Elder",
    "explanation": "Wen is a child of Vy"
  }
]